aiida_lammps/__init__.py
aiida_lammps/utils.py
aiida_lammps/calculations/__init__.py
aiida_lammps/calculations/base.py
aiida_lammps/calculations/raw.py
aiida_lammps/data/__init__.py
aiida_lammps/data/lammps_potentials.json
aiida_lammps/data/potential.py
aiida_lammps/data/trajectory.py
aiida_lammps/parsers/__init__.py
aiida_lammps/parsers/base.py
aiida_lammps/parsers/inputfile.py
aiida_lammps/parsers/raw.py
aiida_lammps/parsers/utils.py
aiida_lammps/parsers/variables_types.json
aiida_lammps/parsers/parse_raw/__init__.py
aiida_lammps/parsers/parse_raw/final_data.py
aiida_lammps/parsers/parse_raw/lammps_output.py
aiida_lammps/parsers/parse_raw/trajectory.py
aiida_lammps/validation/__init__.py
aiida_lammps/validation/utils.py
aiida_lammps/validation/schemas/__init__.py
aiida_lammps/validation/schemas/lammps_schema.json
aiida_lammps/workflows/__init__.py
aiida_lammps/workflows/base.py
aiida_lammps/workflows/md.py
aiida_lammps/workflows/relax.py
aiida_lammps-1.0.2.dist-info/entry_points.txt
aiida_lammps-1.0.2.dist-info/LICENSE
aiida_lammps-1.0.2.dist-info/WHEEL
aiida_lammps-1.0.2.dist-info/METADATA
aiida_lammps-1.0.2.dist-info/RECORD
