Metadata-Version: 2.1
Name: aiida-lammps
Version: 1.0.2
Summary: AiiDA plugin for the LAMMPS code
Keywords: aiida,workflows,lammps
Author-email: Chris Sewell <chrisj_sewell@hotmail.com>, Jonathan Chico <jonathan.chico@sandvik.com>
Requires-Python: >=3.9
Classifier: Development Status :: 4 - Beta
Classifier: License :: OSI Approved :: MIT License
Classifier: Programming Language :: Python
Classifier: Programming Language :: Python :: 3
Classifier: Programming Language :: Python :: 3.9
Classifier: Programming Language :: Python :: 3.10
Classifier: Programming Language :: Python :: 3.11
Classifier: Programming Language :: Python :: 3.12
Classifier: Topic :: Scientific/Engineering :: Chemistry
Classifier: Topic :: Scientific/Engineering :: Physics
Classifier: Framework :: AiiDA
Requires-Dist: aiida-core[atomic_tools]~=2.3
Requires-Dist: importlib_resources
Requires-Dist: jsonschema~=3.2.0
Requires-Dist: numpy
Requires-Dist: packaging
Requires-Dist: python-dateutil
Requires-Dist: sphinx~=6.2.1 ; extra == "docs"
Requires-Dist: sphinx-copybutton~=0.5.2 ; extra == "docs"
Requires-Dist: sphinx-book-theme~=1.0.1 ; extra == "docs"
Requires-Dist: sphinx-click~=5.1.0 ; extra == "docs"
Requires-Dist: sphinx-design~=0.5.0 ; extra == "docs"
Requires-Dist: sphinxcontrib-details-directive~=0.1.0 ; extra == "docs"
Requires-Dist: sphinx-autoapi~=3.0 ; extra == "docs"
Requires-Dist: myst_parser~=2.0.0 ; extra == "docs"
Requires-Dist: furo ; extra == "docs"
Requires-Dist: pre-commit~=2.17 ; extra == "pre-commit"
Requires-Dist: pgtest~=1.3 ; extra == "tests"
Requires-Dist: pytest~=7.4 ; extra == "tests"
Requires-Dist: pytest-regressions~=2.3 ; extra == "tests"
Requires-Dist: pytest-cov ; extra == "tests"
Requires-Dist: coverage ; extra == "tests"
Requires-Dist: pytest-timeout ; extra == "tests"
Requires-Dist: pytest-regressions ; extra == "tests"
Project-URL: Documentation, https://aiida-lammps.readthedocs.io
Project-URL: Source, https://github.com/aiidaplugins/aiida-lammps
Provides-Extra: docs
Provides-Extra: pre-commit
Provides-Extra: tests
